synchro/__init__.py
synchro/cli.py
synchro/sync.py
synchro/utils/__init__.py
synchro/utils/create_cmd.py
synchro/utils/logging.py
synchro/utils/misc.py
synchro/utils/options.py
synchro/utils/paths.py
tests/__init__.py
tests/test_integration/__init__.py
tests/test_integration/test_local_sync.py
tests/test_unit/__init__.py
tests/test_unit/test_utils/__init__.py
tests/test_unit/test_utils/test_create_cmd.py
tests/test_unit/test_utils/test_logging.py
tests/test_unit/test_utils/test_misc.py
tests/utils/__init__.py
tests/utils/utils.py
synchro-0.0.3.dist-info/METADATA
synchro-0.0.3.dist-info/WHEEL
synchro-0.0.3.dist-info/entry_points.txt
synchro-0.0.3.dist-info/top_level.txt
synchro-0.0.3.dist-info/RECORD
