Metadata-Version: 2.1
Name: synchro
Version: 0.0.3
Summary: Customisable file transfers using rsync
Home-page: https://github.com/instituteofcancerresearch/synchro
Author: Adam Tyson
Author-email: code@adamltyson.com
License: UNKNOWN
Project-URL: Source, https://github.com/instituteofcancerresearch/synchro
Project-URL: Tracker, https://github.com/instituteofcancerresearch/synchro/issues
Platform: UNKNOWN
Classifier: Development Status :: 3 - Alpha
Classifier: Intended Audience :: Developers
Classifier: Operating System :: POSIX :: Linux
Classifier: Operating System :: MacOS
Classifier: Programming Language :: Python
Classifier: Programming Language :: Python :: 3 :: Only
Classifier: Programming Language :: Python :: 3.9
Classifier: Programming Language :: Python :: 3.10
Requires-Python: >=3.9
Provides-Extra: dev
Requires-Dist: black ; extra == 'dev'
Requires-Dist: pytest ; extra == 'dev'
Requires-Dist: pytest-cov ; extra == 'dev'
Requires-Dist: bump2version ; extra == 'dev'
Requires-Dist: pre-commit ; extra == 'dev'
Requires-Dist: flake8 ; extra == 'dev'
Requires-Dist: coverage ; extra == 'dev'
Requires-Dist: mypy ; extra == 'dev'
